{
  "start": {
    "message": "Привет! 👋\n\nЯ - «Компас эмоций». Помогу вам разобраться в чувствах, подскажу техники для спокойствия и научу лучше понимать себя.\n\nКак к вам обращаться?",
    "buttons": []
  },
  "user_name": {
    "message": "Рад знакомству, {{Username}}!\n\nПеред тем как начать, я отмечу пару моментов о том, что вы можете здесь получить\n\n<b>Со мной вы сможете:</b> \n✅ Определить, какие эмоции вы испытываете.  \n✅ Узнать, что они значат и как с ними работать.  \n✅ Использовать медитации и техники для успокоения.  \n✅ Вести дневники для осознания своих состояний.",
    "buttons": [
      {"text": "Поехали!", "next_state": "choose_focus"}
    ]
  },
  "choose_focus": {
    "message": "Отлично! Выберите, что для вас сейчас наиболее важно.",
    "buttons": [
      {"text": "🧘 Управлять стрессом", "next_state": "stress_management"},
      {"text": "😌 Перестать срываться на близких", "next_state": "stop_snapping"},
      {"text": "🌀 Найти баланс и спокойствие", "next_state": "find_balance"},
      {"text": "🔍 Лучше понимать свои эмоции", "next_state": "understand_emotions"},
      {"text": "🧩 Другое", "next_state": "other"}
    ]
  },
  "stress_management": {
    "message": "Управление стрессом - это важный навык. У меня есть техники, которые помогут вам расслабиться и снизить напряжение.\n\nДля начала важно понять ваше состояние.\n\nКак вы себя чувствуете сейчас?",
    "buttons": [
      {"text": "😊 Хорошо", "next_state": "good"},
      {"text": "😓 Тревожно", "next_state": "anxious"},
      {"text": "😠 Раздраженно", "next_state": "irritated"},
      {"text": "😞 Апатично", "next_state": "apathetic"},
      {"text": "😐 Непонятно", "next_state": "unclear"}
    ]
  },
  "stop_snapping": {
    "message": "Это трудно, но возможно. Начнем с осознания ваших эмоций, а потом найдём способы справляться с ними.\n\nДля начала важно понять ваше состояние.\n\nКак вы себя чувствуете сейчас?",
    "buttons": [
      {"text": "😊 Хорошо", "next_state": "good"},
      {"text": "😓 Тревожно", "next_state": "anxious"},
      {"text": "😠 Раздраженно", "next_state": "irritated"},
      {"text": "😞 Апатично", "next_state": "apathetic"},
      {"text": "😐 Непонятно", "next_state": "unclear"}
    ]
  },
  "find_balance": {
    "message": "Баланс - это то, что делает жизнь легче. Я буду помогать вам его достичь.\n\nДля начала важно понять ваше состояние.\n\nКак вы себя чувствуете сейчас?",
    "buttons": [
      {"text": "😊 Хорошо", "next_state": "good"},
      {"text": "😓 Тревожно", "next_state": "anxious"},
      {"text": "😠 Раздраженно", "next_state": "irritated"},
      {"text": "😞 Апатично", "next_state": "apathetic"},
      {"text": "😐 Непонятно", "next_state": "unclear"}
    ]
  }
}
